elipy/__init__.py
elipy/core/a2f_calculator.py
elipy/core/constants.py
elipy/core/eliashberg.py
elipy/core/files_handling.py
elipy/core/grid.py
elipy/core/kpt_utils.py
elipy/core/messages.py
elipy/core/mpi.py
elipy-0.1.8.dist-info/LICENSE.txt
elipy-0.1.8.dist-info/METADATA
elipy-0.1.8.dist-info/WHEEL
elipy-0.1.8.dist-info/RECORD
