Metadata-Version: 2.1
Name: elipy
Version: 0.1.8
Summary: Post-processing tool for Abinit >= 9.8.1 aiming to calculate energy-resolved Eliashberg function
License: MIT
Author: Fedor Akhmetov
Author-email: f.akhmetov@utwente.nl
Requires-Python: >=3.10,<4.0
Classifier: License :: OSI Approved :: MIT License
Classifier: Programming Language :: Python :: 3
Classifier: Programming Language :: Python :: 3.10
Classifier: Programming Language :: Python :: 3.11
Requires-Dist: mpi4py (>=3.1.4,<4.0.0)
Requires-Dist: netCDF4 (>=1.5.7,<2.0.0)
Requires-Dist: numba (>=0.56.4,<0.57.0)
Requires-Dist: numpy (>=1.23.5,<2.0.0)
Requires-Dist: scipy (>=1.9.3,<2.0.0)
